{
  "name": "subject",
  "plural": "subjects",
  "base": "PersistedModel",
  "idInjection": true,
  "options": {
    "validateUpsert": true
  },
  "properties": {
    "subName": {
      "type": "string",
      "required": true
    },
    "subCode": {
      "type": "string",
      "required": true
    },
    "subSem": {
      "type": "number",
      "required": true
    }
  },
  "validations": [],
  "relations": {
    "department": {
      "type": "belongsTo",
      "model": "department",
      "foreignKey": "departmentId"
    },
    "faculties": {
      "type": "hasMany",
      "model": "faculty",
      "foreignKey": "subjectId",
      "through": "SubjectFacultyMapping"
    }
  },
  "acls": [],
  "methods": {}
}
